Metadata-Version: 2.1
Name: credopy
Version: 1.1.1
Summary: A Python 3 tool to fetch secure strings from aws parameter store and injecting those into environment variables.
Home-page: https://github.com/MartinWie/CredoPy
Author: MartinWiechmann
Author-email: martin.wiechmann.office@gmail.com
License: MIT
Download-URL: https://github.com/MartinWie/CredoPy/archive/1.1.1.tar.gz
Keywords: aws credo security parameterstore ssm cloud password pydo credopy
Platform: UNKNOWN
Classifier: Development Status :: 5 - Production/Stable
Classifier: Environment :: Console
Classifier: Intended Audience :: Developers
Classifier: License :: OSI Approved :: MIT License
Classifier: Programming Language :: Python :: 3
Classifier: Topic :: Security
Classifier: Operating System :: OS Independent
